quadrilemma/__init__.py
quadrilemma-0.0.1.dist-info/LICENSE
quadrilemma-0.0.1.dist-info/METADATA
quadrilemma-0.0.1.dist-info/WHEEL
quadrilemma-0.0.1.dist-info/top_level.txt
quadrilemma-0.0.1.dist-info/RECORD
