Metadata-Version: 2.1
Name: quadrilemma
Version: 0.0.1
Summary: Yes, No, Unknown or Unknowable?
Author-email: Alexander Fedotov <alex.fedotov@aol.com>
Project-URL: Homepage, https://github.com/quadrilemma/quadrilemma
Project-URL: Bug Tracker, https://github.com/quadrilemma/quadrilemma/issues
Classifier: Programming Language :: Python :: 3
Classifier: License :: OSI Approved :: MIT License
Classifier: Operating System :: OS Independent
Requires-Python: >=3.10
License-File: LICENSE
